LICENSE
README.md
VERSION
requirements.txt
setup.py
aylien_model_serving/__init__.py
aylien_model_serving/app_factory.py
aylien_model_serving/cached_app_factory.py
examples/__init__.py
examples/example_schema_pb2.py
examples/example_serving_handler.py
examples/example_serving_handler_cached.py
examples/example_serving_handler_cached_with_custom_config.py
model_serving.egg-info/PKG-INFO
model_serving.egg-info/SOURCES.txt
model_serving.egg-info/dependency_links.txt
model_serving.egg-info/requires.txt
model_serving.egg-info/top_level.txt
test/__init__.py
test/example_schema_pb2.py
test/test_app_factory.py
test/test_cached_app_factory.py