Metadata-Version: 2.1
Name: model-serving
Version: 2.0.5
Summary: Gunicorn Flask based library for serving ML Models, built by the ml-ops and science team at Aylien
Home-page: UNKNOWN
License: UNKNOWN
Platform: UNKNOWN
